{
  "lastChecked": {
    "caz37OwO": 1774355826,
    "jet0312": 1774361925,
    "TOMATO10": 1774370023,
    "toka0428": 1774105417
  },
  "solvedProblems": {
    "caz37OwO:arc189_c": true,
    "jet0312:abc079_d": true,
    "jet0312:abc075_c": true,
    "jet0312:nikkei2019_final_a": true,
    "jet0312:joi2010ho_a": true,
    "jet0312:abc214_c": true,
    "jet0312:math_and_algorithm_an": true,
    "jet0312:tessoku_book_bl": true,
    "jet0312:abc362_d": true,
    "jet0312:typical90_m": true,
    "TOMATO10:abc144_a": true,
    "caz37OwO:abc304_a": true,
    "TOMATO10:abc138_e": true,
    "TOMATO10:abc139_e": true,
    "caz37OwO:abc445_g": true,
    "caz37OwO:abc324_f": true,
    "caz37OwO:abc242_a": true,
    "caz37OwO:abc242_b": true,
    "caz37OwO:abc242_c": true,
    "caz37OwO:abc242_d": true,
    "jet0312:tessoku_book_bp": true,
    "TOMATO10:abc146_a": true,
    "TOMATO10:abc146_b": true,
    "TOMATO10:abc146_c": true,
    "TOMATO10:abc146_d": true,
    "TOMATO10:abc447_a": true,
    "TOMATO10:abc447_b": true,
    "TOMATO10:abc447_c": true,
    "TOMATO10:abc447_d": true,
    "TOMATO10:abc447_f": true,
    "TOMATO10:abc447_e": true,
    "caz37OwO:abc242_e": true,
    "caz37OwO:abc447_a": true,
    "caz37OwO:abc447_b": true,
    "caz37OwO:abc447_c": true,
    "caz37OwO:abc447_d": true,
    "caz37OwO:abc447_e": true,
    "caz37OwO:abc447_f": true,
    "toka0428:abc447_a": true,
    "toka0428:abc447_b": true,
    "toka0428:abc447_c": true,
    "toka0428:abc447_d": true,
    "toka0428:abc447_e": true,
    "jet0312:abc447_a": true,
    "jet0312:abc447_b": true,
    "jet0312:abc447_e": true,
    "TOMATO10:abc146_f": true,
    "TOMATO10:abc146_e": true,
    "TOMATO10:abc145_e": true,
    "caz37OwO:arc215_e": true,
    "caz37OwO:abc444_f": true,
    "caz37OwO:abc431_g": true,
    "jet0312:abc447_c": true,
    "jet0312:abc447_d": true,
    "jet0312:awc0003_a": true,
    "jet0312:awc0003_b": true,
    "jet0312:awc0003_c": true,
    "caz37OwO:abc364_g": true,
    "caz37OwO:abc388_g": true,
    "jet0312:abc038_c": true,
    "TOMATO10:abc148_f": true,
    "TOMATO10:abc151_e": true,
    "TOMATO10:abc152_e": true,
    "TOMATO10:abc150_d": true,
    "caz37OwO:abc374_f": true,
    "caz37OwO:abc366_g": true,
    "TOMATO10:abc141_e": true,
    "TOMATO10:abc144_e": true,
    "caz37OwO:abc352_g": true,
    "jet0312:awc0005_a": true,
    "jet0312:awc0005_b": true,
    "jet0312:awc0005_c": true,
    "TOMATO10:abc143_e": true,
    "TOMATO10:abc147_e": true,
    "TOMATO10:abc153_f": true,
    "TOMATO10:abc154_f": true,
    "TOMATO10:abc156_e": true,
    "TOMATO10:abc157_d": true,
    "TOMATO10:abc157_e": true,
    "jet0312:abc378_d": true,
    "caz37OwO:abc365_f": true,
    "caz37OwO:abc388_f": true,
    "caz37OwO:abc362_f": true,
    "TOMATO10:abc161_f": true,
    "caz37OwO:abc360_f": true,
    "TOMATO10:abc162_e": true,
    "TOMATO10:abc162_f": true,
    "caz37OwO:abc359_g": true,
    "toka0428:abc313_g": true,
    "jet0312:awc0006_a": true,
    "jet0312:awc0006_b": true,
    "jet0312:awc0006_c": true,
    "caz37OwO:abc408_g": true,
    "caz37OwO:abc419_g": true,
    "toka0428:abc341_d": true,
    "caz37OwO:abc321_g": true,
    "TOMATO10:abc164_d": true,
    "TOMATO10:abc169_e": true,
    "jet0312:awc0007_a": true,
    "TOMATO10:abc171_f": true,
    "TOMATO10:abc174_e": true,
    "caz37OwO:abc324_g": true,
    "toka0428:agc067_a": true,
    "jet0312:awc0007_b": true,
    "jet0312:awc0007_c": true,
    "caz37OwO:abc440_f": true,
    "toka0428:arc152_d": true,
    "caz37OwO:abc433_g": true,
    "caz37OwO:abc438_g": true,
    "TOMATO10:abc448_a": true,
    "TOMATO10:abc448_b": true,
    "TOMATO10:abc448_c": true,
    "TOMATO10:abc448_d": true,
    "TOMATO10:abc448_e": true,
    "TOMATO10:abc448_f": true,
    "caz37OwO:abc448_a": true,
    "caz37OwO:abc448_b": true,
    "caz37OwO:abc448_c": true,
    "caz37OwO:abc448_d": true,
    "caz37OwO:abc448_e": true,
    "caz37OwO:abc448_f": true,
    "toka0428:abc448_a": true,
    "toka0428:abc448_b": true,
    "toka0428:abc448_c": true,
    "toka0428:abc448_d": true,
    "toka0428:abc448_e": true,
    "jet0312:abc448_a": true,
    "jet0312:abc448_b": true,
    "jet0312:abc448_c": true,
    "TOMATO10:abc175_d": true,
    "TOMATO10:abc256_d": true,
    "caz37OwO:abc221_a": true,
    "TOMATO10:abc168_e": true,
    "TOMATO10:abc173_f": true,
    "TOMATO10:abc170_f": true,
    "toka0428:agc041_c": true,
    "jet0312:abc296_c": true,
    "jet0312:abc295_c": true,
    "jet0312:abc297_c": true,
    "TOMATO10:abc175_e": true,
    "TOMATO10:abc176_d": true,
    "TOMATO10:abc176_e": true,
    "toka0428:agc051_a": true,
    "caz37OwO:abc400_g": true,
    "jet0312:abc298_c": true,
    "jet0312:abc299_c": true,
    "jet0312:abc300_c": true,
    "TOMATO10:abc177_e": true,
    "TOMATO10:abc178_e": true,
    "TOMATO10:abc181_e": true,
    "TOMATO10:abc182_e": true,
    "TOMATO10:abc185_e": true,
    "caz37OwO:abc440_g": true,
    "caz37OwO:abc304_b": true,
    "caz37OwO:abc361_g": true,
    "TOMATO10:abc191_e": true,
    "TOMATO10:abc187_f": true,
    "TOMATO10:abc189_e": true,
    "caz37OwO:abc435_g": true,
    "caz37OwO:abc432_f": true,
    "caz37OwO:abc430_g": true,
    "jet0312:abc208_c": true,
    "caz37OwO:abc442_g": true,
    "caz37OwO:abc418_f": true,
    "jet0312:abc202_c": true,
    "jet0312:abc202_b": true,
    "jet0312:abc202_a": true,
    "caz37OwO:abc371_g": true,
    "caz37OwO:abc318_a": true,
    "caz37OwO:abc317_a": true,
    "caz37OwO:abc315_a": true,
    "caz37OwO:abc318_b": true,
    "caz37OwO:abc317_b": true,
    "caz37OwO:abc315_b": true,
    "caz37OwO:abc315_c": true,
    "caz37OwO:abc318_c": true,
    "caz37OwO:abc317_d": true,
    "caz37OwO:abc315_e": true,
    "caz37OwO:abc318_e": true,
    "caz37OwO:abc318_d": true,
    "caz37OwO:abc317_e": true,
    "caz37OwO:abc315_d": true,
    "caz37OwO:abc315_f": true,
    "caz37OwO:abc318_f": true,
    "caz37OwO:abc317_c": true,
    "jet0312:abc069_a": true,
    "jet0312:abc268_a": true,
    "TOMATO10:abc196_a": true,
    "TOMATO10:abc196_b": true,
    "TOMATO10:abc196_c": true,
    "TOMATO10:abc196_d": true,
    "TOMATO10:abc449_a": true,
    "TOMATO10:abc449_b": true,
    "TOMATO10:abc449_c": true,
    "TOMATO10:abc449_e": true,
    "TOMATO10:abc449_d": true,
    "TOMATO10:abc196_e": true,
    "caz37OwO:practice2_a": true,
    "caz37OwO:practice2_b": true,
    "caz37OwO:practice2_d": true,
    "caz37OwO:abc449_a": true,
    "caz37OwO:abc449_b": true,
    "caz37OwO:abc449_c": true,
    "caz37OwO:abc449_d": true,
    "caz37OwO:abc449_e": true,
    "caz37OwO:abc449_f": true,
    "toka0428:abc449_a": true,
    "toka0428:abc449_b": true,
    "toka0428:abc449_c": true,
    "toka0428:abc449_d": true,
    "jet0312:abc449_a": true,
    "jet0312:abc449_b": true,
    "jet0312:abc449_c": true,
    "toka0428:agc075_a": true,
    "caz37OwO:waipc_qual_a": true,
    "caz37OwO:waipc_qual_b": true,
    "jet0312:abc220_c": true,
    "caz37OwO:abc314_a": true,
    "jet0312:abc221_c": true,
    "jet0312:abc222_c": true,
    "TOMATO10:waipc_qual_a": true,
    "TOMATO10:abc194_d": true,
    "TOMATO10:abc194_e": true,
    "caz37OwO:abc314_b": true,
    "TOMATO10:abc195_e": true,
    "caz37OwO:abc449_g": true,
    "jet0312:abc183_d": true,
    "jet0312:abc014_3": true,
    "TOMATO10:abc198_e": true,
    "TOMATO10:abc199_d": true,
    "TOMATO10:abc201_e": true,
    "jet0312:abc188_d": true,
    "TOMATO10:abc140_e": true,
    "caz37OwO:abc415_g": true,
    "toka0428:arc114_b": true,
    "jet0312:abc223_c": true,
    "jet0312:tessoku_book_t": true,
    "jet0312:tessoku_book_cs": true,
    "TOMATO10:abc150_e": true,
    "caz37OwO:abc376_f": true,
    "jet0312:abc224_c": true,
    "jet0312:awc0007_d": true,
    "caz37OwO:abc409_g": true,
    "caz37OwO:abc377_f": true,
    "TOMATO10:abc154_e": true,
    "caz37OwO:abc341_g": true,
    "TOMATO10:abc155_d": true,
    "TOMATO10:abc200_e": true,
    "caz37OwO:abc313_a": true,
    "caz37OwO:abc312_a": true,
    "caz37OwO:abc311_a": true,
    "caz37OwO:abc311_b": true,
    "caz37OwO:abc313_b": true,
    "caz37OwO:abc312_b": true,
    "caz37OwO:abc314_c": true,
    "caz37OwO:abc311_c": true,
    "caz37OwO:abc314_d": true,
    "caz37OwO:abc313_c": true,
    "caz37OwO:abc312_c": true,
    "caz37OwO:abc311_d": true,
    "caz37OwO:abc312_d": true,
    "caz37OwO:abc311_e": true,
    "TOMATO10:abc269_a": true,
    "TOMATO10:abc269_b": true,
    "TOMATO10:abc269_c": true,
    "caz37OwO:abc313_e": true,
    "TOMATO10:abc450_a": true,
    "TOMATO10:abc450_b": true,
    "TOMATO10:abc450_c": true,
    "TOMATO10:abc450_d": true,
    "caz37OwO:abc450_a": true,
    "caz37OwO:abc450_b": true,
    "caz37OwO:abc450_c": true,
    "caz37OwO:abc450_d": true,
    "caz37OwO:abc450_e": true,
    "caz37OwO:abc450_f": true,
    "toka0428:abc450_a": true,
    "toka0428:abc450_b": true,
    "toka0428:abc450_c": true,
    "toka0428:abc450_d": true,
    "jet0312:abc450_a": true,
    "jet0312:abc450_b": true,
    "jet0312:abc450_d": true,
    "toka0428:abc102_a": true,
    "jet0312:abc450_c": true,
    "caz37OwO:arc213_b": true,
    "caz37OwO:arc216_a": true,
    "caz37OwO:arc216_b": true,
    "jet0312:abc180_e": true,
    "TOMATO10:abc204_e": true,
    "TOMATO10:abc207_e": true,
    "caz37OwO:fps_24_g": true,
    "caz37OwO:fps_24_h": true,
    "caz37OwO:fps_24_i": true,
    "caz37OwO:dp_i": true,
    "caz37OwO:dp_j": true,
    "caz37OwO:dp_k": true,
    "caz37OwO:dp_l": true,
    "caz37OwO:dp_m": true,
    "caz37OwO:dp_n": true,
    "caz37OwO:dp_o": true,
    "caz37OwO:dp_p": true,
    "caz37OwO:dp_q": true,
    "caz37OwO:dp_r": true,
    "caz37OwO:dp_s": true,
    "caz37OwO:dp_t": true,
    "caz37OwO:dp_u": true,
    "caz37OwO:dp_v": true,
    "caz37OwO:dp_w": true,
    "caz37OwO:dp_x": true,
    "jet0312:practice2_d": true,
    "jet0312:tessoku_book_bq": true,
    "jet0312:tessoku_book_w": true,
    "TOMATO10:abc211_e": true,
    "TOMATO10:abc218_f": true,
    "caz37OwO:dp_y": true
  }
}